has_auth_client/__init__.py
has_auth_client/client.py
has_auth_client/setup.py
has_auth_client-0.1.6.dist-info/METADATA
has_auth_client-0.1.6.dist-info/WHEEL
has_auth_client-0.1.6.dist-info/top_level.txt
has_auth_client-0.1.6.dist-info/RECORD
